{
    "BusStopCode": "04159",
    "Services": [
        {
            "NextBus": {
                "DestinationCode": "10499",
                "EstimatedArrival": "2023-09-03T17:32:55+08:00",
                "Feature": "WAB",
                "Latitude": "1.3051498333333333",
                "Load": "SEA",
                "Longitude": "103.86048183333334",
                "OriginCode": "77009",
                "Type": "DD",
                "VisitNumber": "1"
            },
            "NextBus2": {
                "DestinationCode": "10499",
                "EstimatedArrival": "2023-09-03T17:46:03+08:00",
                "Feature": "WAB",
                "Latitude": "1.3007806666666666",
                "Load": "SEA",
                "Longitude": "103.88626966666666",
                "OriginCode": "77009",
                "Type": "DD",
                "VisitNumber": "1"
            },
            "NextBus3": {
                "DestinationCode": "10499",
                "EstimatedArrival": "2023-09-03T17:51:40+08:00",
                "Feature": "WAB",
                "Latitude": "1.3035255000000001",
                "Load": "SEA",
                "Longitude": "103.90127333333334",
                "OriginCode": "77009",
                "Type": "DD",
                "VisitNumber": "1"
            },
            "Operator": "GAS",
            "ServiceNo": "12"
        },
        {
            "NextBus": {
                "DestinationCode": "10499",
                "EstimatedArrival": "2023-09-03T17:38:06+08:00",
                "Feature": "WAB",
                "Latitude": "1.3009971666666666",
                "Load": "SEA",
                "Longitude": "103.90914533333333",
                "OriginCode": "77009",
                "Type": "DD",
                "VisitNumber": "1"
            },
            "NextBus2": {
                "DestinationCode": "10499",
                "EstimatedArrival": "2023-09-03T18:05:37+08:00",
                "Feature": "WAB",
                "Latitude": "1.3541913333333333",
                "Load": "SEA",
                "Longitude": "103.95549066666666",
                "OriginCode": "77009",
                "Type": "DD",
                "VisitNumber": "1"
            },
            "NextBus3": {
                "DestinationCode": "",
                "EstimatedArrival": "",
                "Feature": "",
                "Latitude": "",
                "Load": "",
                "Longitude": "",
                "OriginCode": "",
                "Type": "",
                "VisitNumber": ""
            },
            "Operator": "GAS",
            "ServiceNo": "12e"
        },
        {
            "NextBus": {
                "DestinationCode": "17009",
                "EstimatedArrival": "2023-09-03T17:24:00+08:00",
                "Feature": "WAB",
                "Latitude": "1.2962896666666666",
                "Load": "SEA",
                "Longitude": "103.85150216666666",
                "OriginCode": "64009",
                "Type": "DD",
                "VisitNumber": "1"
            },
            "NextBus2": {
                "DestinationCode": "17009",
                "EstimatedArrival": "2023-09-03T17:31:16+08:00",
                "Feature": "WAB",
                "Latitude": "1.3064955",
                "Load": "SEA",
                "Longitude": "103.8560585",
                "OriginCode": "64009",
                "Type": "DD",
                "VisitNumber": "1"
            },
            "NextBus3": {
                "DestinationCode": "17009",
                "EstimatedArrival": "2023-09-03T17:45:36+08:00",
                "Feature": "WAB",
                "Latitude": "1.331002",
                "Load": "SEA",
                "Longitude": "103.8691885",
                "OriginCode": "64009",
                "Type": "DD",
                "VisitNumber": "1"
            },
            "Operator": "SBST",
            "ServiceNo": "147"
        },
        {
            "NextBus": {
                "DestinationCode": "10499",
                "EstimatedArrival": "2023-09-03T17:32:58+08:00",
                "Feature": "WAB",
                "Latitude": "1.3023118333333334",
                "Load": "SEA",
                "Longitude": "103.83685483333333",
                "OriginCode": "44009",
                "Type": "DD",
                "VisitNumber": "1"
            },
            "NextBus2": {
                "DestinationCode": "10499",
                "EstimatedArrival": "2023-09-03T17:42:16+08:00",
                "Feature": "WAB",
                "Latitude": "1.3203285",
                "Load": "SEA",
                "Longitude": "103.82550333333333",
                "OriginCode": "44009",
                "Type": "SD",
                "VisitNumber": "1"
            },
            "NextBus3": {
                "DestinationCode": "10499",
                "EstimatedArrival": "2023-09-03T17:43:55+08:00",
                "Feature": "WAB",
                "Latitude": "1.322601",
                "Load": "SEA",
                "Longitude": "103.82617183333333",
                "OriginCode": "44009",
                "Type": "DD",
                "VisitNumber": "1"
            },
            "Operator": "SMRT",
            "ServiceNo": "190"
        },
        {
            "NextBus": {
                "DestinationCode": "10499",
                "EstimatedArrival": "2023-09-03T17:29:16+08:00",
                "Feature": "WAB",
                "Latitude": "1.3006236666666666",
                "Load": "SEA",
                "Longitude": "103.85595366666666",
                "OriginCode": "99009",
                "Type": "DD",
                "VisitNumber": "1"
            },
            "NextBus2": {
                "DestinationCode": "10499",
                "EstimatedArrival": "2023-09-03T17:38:41+08:00",
                "Feature": "WAB",
                "Latitude": "1.3105215000000001",
                "Load": "SEA",
                "Longitude": "103.87282916666666",
                "OriginCode": "99009",
                "Type": "DD",
                "VisitNumber": "1"
            },
            "NextBus3": {
                "DestinationCode": "10499",
                "EstimatedArrival": "2023-09-03T17:54:27+08:00",
                "Feature": "WAB",
                "Latitude": "1.317162",
                "Load": "SEA",
                "Longitude": "103.90293383333334",
                "OriginCode": "99009",
                "Type": "DD",
                "VisitNumber": "1"
            },
            "Operator": "GAS",
            "ServiceNo": "2"
        },
        {
            "NextBus": {
                "DestinationCode": "16009",
                "EstimatedArrival": "2023-09-03T17:39:59+08:00",
                "Feature": "WAB",
                "Latitude": "1.3101115",
                "Load": "SDA",
                "Longitude": "103.87555416666666",
                "OriginCode": "84009",
                "Type": "SD",
                "VisitNumber": "1"
            },
            "NextBus2": {
                "DestinationCode": "16009",
                "EstimatedArrival": "2023-09-03T17:52:06+08:00",
                "Feature": "WAB",
                "Latitude": "1.3109458333333333",
                "Load": "SEA",
                "Longitude": "103.90132816666667",
                "OriginCode": "84009",
                "Type": "SD",
                "VisitNumber": "1"
            },
            "NextBus3": {
                "DestinationCode": "16009",
                "EstimatedArrival": "2023-09-03T18:04:13+08:00",
                "Feature": "WAB",
                "Latitude": "0.0",
                "Load": "SEA",
                "Longitude": "0.0",
                "OriginCode": "84009",
                "Type": "SD",
                "VisitNumber": "1"
            },
            "Operator": "SBST",
            "ServiceNo": "33"
        }
    ],
    "odata.metadata": "http://datamall2.mytransport.sg/ltaodataservice/$metadata#BusArrivalv2/@Element"
}