{
    "BusStopCode": "10331",
    "Services": [
        {
            "NextBus": {
                "DestinationCode": "11379",
                "EstimatedArrival": "2023-09-04T18:59:35+08:00",
                "Feature": "WAB",
                "Latitude": "1.2759295",
                "Load": "SEA",
                "Longitude": "103.8152025",
                "OriginCode": "52009",
                "Type": "DD",
                "VisitNumber": "1"
            },
            "NextBus2": {
                "DestinationCode": "11379",
                "EstimatedArrival": "2023-09-04T19:09:22+08:00",
                "Feature": "WAB",
                "Latitude": "1.2655421666666666",
                "Load": "SEA",
                "Longitude": "103.82207266666667",
                "OriginCode": "52009",
                "Type": "SD",
                "VisitNumber": "1"
            },
            "NextBus3": {
                "DestinationCode": "11379",
                "EstimatedArrival": "2023-09-04T19:15:29+08:00",
                "Feature": "WAB",
                "Latitude": "1.2721818333333332",
                "Load": "SEA",
                "Longitude": "103.83866683333333",
                "OriginCode": "52009",
                "Type": "SD",
                "VisitNumber": "1"
            },
            "Operator": "SBST",
            "ServiceNo": "145"
        },
        {
            "NextBus": {
                "DestinationCode": "80009",
                "EstimatedArrival": "2023-09-04T19:10:43+08:00",
                "Feature": "WAB",
                "Latitude": "1.2747753333333334",
                "Load": "SEA",
                "Longitude": "103.796931",
                "OriginCode": "17009",
                "Type": "SD",
                "VisitNumber": "1"
            },
            "NextBus2": {
                "DestinationCode": "80009",
                "EstimatedArrival": "2023-09-04T19:19:37+08:00",
                "Feature": "WAB",
                "Latitude": "1.2895988333333332",
                "Load": "SEA",
                "Longitude": "103.7728785",
                "OriginCode": "17009",
                "Type": "SD",
                "VisitNumber": "1"
            },
            "NextBus3": {
                "DestinationCode": "80009",
                "EstimatedArrival": "2023-09-04T19:36:28+08:00",
                "Feature": "WAB",
                "Latitude": "0.0",
                "Load": "SEA",
                "Longitude": "0.0",
                "OriginCode": "17009",
                "Type": "SD",
                "VisitNumber": "1"
            },
            "Operator": "SBST",
            "ServiceNo": "175"
        },
        {
            "NextBus": {
                "DestinationCode": "10009",
                "EstimatedArrival": "2023-09-04T19:06:05+08:00",
                "Feature": "WAB",
                "Latitude": "1.2743205",
                "Load": "SEA",
                "Longitude": "103.79842683333334",
                "OriginCode": "45009",
                "Type": "DD",
                "VisitNumber": "1"
            },
            "NextBus2": {
                "DestinationCode": "10009",
                "EstimatedArrival": "2023-09-04T19:12:42+08:00",
                "Feature": "WAB",
                "Latitude": "1.2844965",
                "Load": "SEA",
                "Longitude": "103.78042166666667",
                "OriginCode": "45009",
                "Type": "DD",
                "VisitNumber": "1"
            },
            "NextBus3": {
                "DestinationCode": "10009",
                "EstimatedArrival": "2023-09-04T19:20:33+08:00",
                "Feature": "WAB",
                "Latitude": "1.2994453333333333",
                "Load": "SEA",
                "Longitude": "103.76335816666666",
                "OriginCode": "45009",
                "Type": "DD",
                "VisitNumber": "1"
            },
            "Operator": "SMRT",
            "ServiceNo": "176"
        },
        {
            "NextBus": {
                "DestinationCode": "10009",
                "EstimatedArrival": "2023-09-04T18:57:56+08:00",
                "Feature": "WAB",
                "Latitude": "1.2784578333333334",
                "Load": "SEA",
                "Longitude": "103.81686816666667",
                "OriginCode": "10009",
                "Type": "SD",
                "VisitNumber": "1"
            },
            "NextBus2": {
                "DestinationCode": "10009",
                "EstimatedArrival": "2023-09-04T19:02:56+08:00",
                "Feature": "WAB",
                "Latitude": "1.2748491666666668",
                "Load": "SEA",
                "Longitude": "103.82115966666667",
                "OriginCode": "10009",
                "Type": "SD",
                "VisitNumber": "1"
            },
            "NextBus3": {
                "DestinationCode": "10009",
                "EstimatedArrival": "2023-09-04T19:15:24+08:00",
                "Feature": "WAB",
                "Latitude": "0.0",
                "Load": "SEA",
                "Longitude": "0.0",
                "OriginCode": "10009",
                "Type": "SD",
                "VisitNumber": "1"
            },
            "Operator": "SBST",
            "ServiceNo": "272"
        },
        {
            "NextBus": {
                "DestinationCode": "10009",
                "EstimatedArrival": "2023-09-04T18:59:06+08:00",
                "Feature": "WAB",
                "Latitude": "1.2782246666666666",
                "Load": "SEA",
                "Longitude": "103.81651233333334",
                "OriginCode": "10009",
                "Type": "SD",
                "VisitNumber": "1"
            },
            "NextBus2": {
                "DestinationCode": "10009",
                "EstimatedArrival": "2023-09-04T19:02:58+08:00",
                "Feature": "WAB",
                "Latitude": "1.2730081666666666",
                "Load": "SEA",
                "Longitude": "103.80919133333333",
                "OriginCode": "10009",
                "Type": "SD",
                "VisitNumber": "1"
            },
            "NextBus3": {
                "DestinationCode": "10009",
                "EstimatedArrival": "2023-09-04T19:09:45+08:00",
                "Feature": "WAB",
                "Latitude": "1.275056",
                "Load": "SEA",
                "Longitude": "103.81477866666667",
                "OriginCode": "10009",
                "Type": "SD",
                "VisitNumber": "1"
            },
            "Operator": "SBST",
            "ServiceNo": "273"
        },
        {
            "NextBus": {
                "DestinationCode": "10009",
                "EstimatedArrival": "2023-09-04T19:08:08+08:00",
                "Feature": "WAB",
                "Latitude": "1.2725643333333334",
                "Load": "SEA",
                "Longitude": "103.80263733333334",
                "OriginCode": "53009",
                "Type": "SD",
                "VisitNumber": "1"
            },
            "NextBus2": {
                "DestinationCode": "10009",
                "EstimatedArrival": "2023-09-04T19:17:58+08:00",
                "Feature": "WAB",
                "Latitude": "1.2655215",
                "Load": "SEA",
                "Longitude": "103.82237266666667",
                "OriginCode": "53009",
                "Type": "SD",
                "VisitNumber": "1"
            },
            "NextBus3": {
                "DestinationCode": "10009",
                "EstimatedArrival": "2023-09-04T19:34:41+08:00",
                "Feature": "WAB",
                "Latitude": "1.2942186666666666",
                "Load": "SEA",
                "Longitude": "103.8547665",
                "OriginCode": "53009",
                "Type": "SD",
                "VisitNumber": "1"
            },
            "Operator": "SBST",
            "ServiceNo": "57"
        }
    ],
    "odata.metadata": "http://datamall2.mytransport.sg/ltaodataservice/$metadata#BusArrivalv2/@Element"
}