{
    "BusStopCode": "14349",
    "Services": [
        {
            "NextBus": {
                "DestinationCode": "10499",
                "EstimatedArrival": "2023-09-04T19:05:56+08:00",
                "Feature": "WAB",
                "Latitude": "1.2811986666666666",
                "Load": "SEA",
                "Longitude": "103.802238",
                "OriginCode": "10499",
                "Type": "SD",
                "VisitNumber": "1"
            },
            "NextBus2": {
                "DestinationCode": "10499",
                "EstimatedArrival": "2023-09-04T19:19:51+08:00",
                "Feature": "WAB",
                "Latitude": "1.2884929999999999",
                "Load": "SEA",
                "Longitude": "103.82093766666667",
                "OriginCode": "10499",
                "Type": "SD",
                "VisitNumber": "1"
            },
            "NextBus3": {
                "DestinationCode": "10499",
                "EstimatedArrival": "2023-09-04T19:30:03+08:00",
                "Feature": "WAB",
                "Latitude": "0.0",
                "Load": "SEA",
                "Longitude": "0.0",
                "OriginCode": "10499",
                "Type": "SD",
                "VisitNumber": "1"
            },
            "Operator": "SBST",
            "ServiceNo": "120"
        },
        {
            "NextBus": {
                "DestinationCode": "14009",
                "EstimatedArrival": "2023-09-04T19:02:27+08:00",
                "Feature": "WAB",
                "Latitude": "1.2749196666666667",
                "Load": "SEA",
                "Longitude": "103.82053133333334",
                "OriginCode": "52499",
                "Type": "SD",
                "VisitNumber": "1"
            },
            "NextBus2": {
                "DestinationCode": "14009",
                "EstimatedArrival": "2023-09-04T19:05:26+08:00",
                "Feature": "WAB",
                "Latitude": "1.2726533333333334",
                "Load": "SDA",
                "Longitude": "103.82371433333333",
                "OriginCode": "52499",
                "Type": "SD",
                "VisitNumber": "1"
            },
            "NextBus3": {
                "DestinationCode": "14009",
                "EstimatedArrival": "2023-09-04T19:18:47+08:00",
                "Feature": "WAB",
                "Latitude": "1.283086",
                "Load": "SDA",
                "Longitude": "103.8425315",
                "OriginCode": "52499",
                "Type": "SD",
                "VisitNumber": "1"
            },
            "Operator": "SBST",
            "ServiceNo": "124"
        },
        {
            "NextBus": {
                "DestinationCode": "10009",
                "EstimatedArrival": "2023-09-04T18:58:17+08:00",
                "Feature": "WAB",
                "Latitude": "1.275893",
                "Load": "SEA",
                "Longitude": "103.81350233333333",
                "OriginCode": "10009",
                "Type": "SD",
                "VisitNumber": "1"
            },
            "NextBus2": {
                "DestinationCode": "10009",
                "EstimatedArrival": "2023-09-04T19:01:35+08:00",
                "Feature": "WAB",
                "Latitude": "1.2800708333333333",
                "Load": "SEA",
                "Longitude": "103.81766366666666",
                "OriginCode": "10009",
                "Type": "SD",
                "VisitNumber": "1"
            },
            "NextBus3": {
                "DestinationCode": "10009",
                "EstimatedArrival": "2023-09-04T19:04:06+08:00",
                "Feature": "WAB",
                "Latitude": "0.0",
                "Load": "SEA",
                "Longitude": "0.0",
                "OriginCode": "10009",
                "Type": "SD",
                "VisitNumber": "1"
            },
            "Operator": "SBST",
            "ServiceNo": "273"
        }
    ],
    "odata.metadata": "http://datamall2.mytransport.sg/ltaodataservice/$metadata#BusArrivalv2/@Element"
}