{
    "BusStopCode": "17329",
    "Services": [
        {
            "NextBus": {
                "DestinationCode": "10009",
                "EstimatedArrival": "2023-09-04T19:04:21+08:00",
                "Feature": "WAB",
                "Latitude": "1.3195053333333333",
                "Load": "SEA",
                "Longitude": "103.7446575",
                "OriginCode": "45009",
                "Type": "SD",
                "VisitNumber": "1"
            },
            "NextBus2": {
                "DestinationCode": "10009",
                "EstimatedArrival": "2023-09-04T19:14:02+08:00",
                "Feature": "WAB",
                "Latitude": "1.3357473333333334",
                "Load": "SEA",
                "Longitude": "103.7390035",
                "OriginCode": "45009",
                "Type": "SD",
                "VisitNumber": "1"
            },
            "NextBus3": {
                "DestinationCode": "10009",
                "EstimatedArrival": "2023-09-04T19:20:54+08:00",
                "Feature": "WAB",
                "Latitude": "1.3447441666666666",
                "Load": "SEA",
                "Longitude": "103.74625866666666",
                "OriginCode": "45009",
                "Type": "SD",
                "VisitNumber": "1"
            },
            "Operator": "SMRT",
            "ServiceNo": "176"
        }
    ],
    "odata.metadata": "http://datamall2.mytransport.sg/ltaodataservice/$metadata#BusArrivalv2/@Element"
}