{
    "BusStopCode": "20179",
    "Services": [
        {
            "NextBus": {
                "DestinationCode": "52009",
                "EstimatedArrival": "2023-09-04T19:01:16+08:00",
                "Feature": "WAB",
                "Latitude": "1.3218758333333334",
                "Load": "SEA",
                "Longitude": "103.74170833333334",
                "OriginCode": "28009",
                "Type": "DD",
                "VisitNumber": "1"
            },
            "NextBus2": {
                "DestinationCode": "52009",
                "EstimatedArrival": "2023-09-04T19:11:41+08:00",
                "Feature": "WAB",
                "Latitude": "1.3353556666666666",
                "Load": "SEA",
                "Longitude": "103.73947016666666",
                "OriginCode": "28009",
                "Type": "DD",
                "VisitNumber": "1"
            },
            "NextBus3": {
                "DestinationCode": "52009",
                "EstimatedArrival": "2023-09-04T19:12:37+08:00",
                "Feature": "WAB",
                "Latitude": "0.0",
                "Load": "SEA",
                "Longitude": "0.0",
                "OriginCode": "28009",
                "Type": "SD",
                "VisitNumber": "1"
            },
            "Operator": "TTS",
            "ServiceNo": "143"
        },
        {
            "NextBus": {
                "DestinationCode": "28009",
                "EstimatedArrival": "2023-09-04T18:58:48+08:00",
                "Feature": "WAB",
                "Latitude": "1.3202443333333334",
                "Load": "SEA",
                "Longitude": "103.7382865",
                "OriginCode": "28009",
                "Type": "SD",
                "VisitNumber": "1"
            },
            "NextBus2": {
                "DestinationCode": "28009",
                "EstimatedArrival": "2023-09-04T19:11:40+08:00",
                "Feature": "WAB",
                "Latitude": "1.335328",
                "Load": "SEA",
                "Longitude": "103.7392405",
                "OriginCode": "28009",
                "Type": "SD",
                "VisitNumber": "1"
            },
            "NextBus3": {
                "DestinationCode": "28009",
                "EstimatedArrival": "2023-09-04T19:24:20+08:00",
                "Feature": "WAB",
                "Latitude": "0.0",
                "Load": "SEA",
                "Longitude": "0.0",
                "OriginCode": "28009",
                "Type": "SD",
                "VisitNumber": "1"
            },
            "Operator": "TTS",
            "ServiceNo": "143M"
        },
        {
            "NextBus": {
                "DestinationCode": "28211",
                "EstimatedArrival": "2023-09-04T19:10:20+08:00",
                "Feature": "WAB",
                "Latitude": "1.3002061666666667",
                "Load": "SEA",
                "Longitude": "103.74693733333334",
                "OriginCode": "28301",
                "Type": "DD",
                "VisitNumber": "1"
            },
            "NextBus2": {
                "DestinationCode": "28211",
                "EstimatedArrival": "2023-09-04T19:17:06+08:00",
                "Feature": "WAB",
                "Latitude": "1.310999",
                "Load": "SEA",
                "Longitude": "103.7576635",
                "OriginCode": "28301",
                "Type": "DD",
                "VisitNumber": "1"
            },
            "NextBus3": {
                "DestinationCode": "28211",
                "EstimatedArrival": "2023-09-04T19:23:40+08:00",
                "Feature": "WAB",
                "Latitude": "1.3124316666666667",
                "Load": "SEA",
                "Longitude": "103.76753283333333",
                "OriginCode": "28301",
                "Type": "DD",
                "VisitNumber": "1"
            },
            "Operator": "TTS",
            "ServiceNo": "78"
        }
    ],
    "odata.metadata": "http://datamall2.mytransport.sg/ltaodataservice/$metadata#BusArrivalv2/@Element"
}