{
    "BusStopCode": "43609",
    "Services": [
        {
            "NextBus": {
                "DestinationCode": "43009",
                "EstimatedArrival": "2023-09-03T17:38:20+08:00",
                "Feature": "WAB",
                "Latitude": "1.3766056666666666",
                "Load": "SEA",
                "Longitude": "103.740801",
                "OriginCode": "44009",
                "Type": "DD",
                "VisitNumber": "1"
            },
            "NextBus2": {
                "DestinationCode": "43009",
                "EstimatedArrival": "2023-09-03T17:48:47+08:00",
                "Feature": "WAB",
                "Latitude": "1.3846641666666666",
                "Load": "SEA",
                "Longitude": "103.74504066666667",
                "OriginCode": "44009",
                "Type": "DD",
                "VisitNumber": "1"
            },
            "NextBus3": {
                "DestinationCode": "43009",
                "EstimatedArrival": "2023-09-03T17:59:30+08:00",
                "Feature": "WAB",
                "Latitude": "0.0",
                "Load": "SEA",
                "Longitude": "0.0",
                "OriginCode": "44009",
                "Type": "DD",
                "VisitNumber": "1"
            },
            "Operator": "SMRT",
            "ServiceNo": "991"
        }
    ],
    "odata.metadata": "http://datamall2.mytransport.sg/ltaodataservice/$metadata#BusArrivalv2/@Element"
}