{
    "BusStopCode": "54049",
    "Services": [
        {
            "NextBus": {
                "DestinationCode": "94009",
                "EstimatedArrival": "2023-09-03T17:29:41+08:00",
                "Feature": "WAB",
                "Latitude": "0.0",
                "Load": "SEA",
                "Longitude": "0.0",
                "OriginCode": "55509",
                "Type": "SD",
                "VisitNumber": "1"
            },
            "NextBus2": {
                "DestinationCode": "94009",
                "EstimatedArrival": "2023-09-03T17:41:01+08:00",
                "Feature": "WAB",
                "Latitude": "0.0",
                "Load": "SEA",
                "Longitude": "0.0",
                "OriginCode": "55509",
                "Type": "SD",
                "VisitNumber": "1"
            },
            "NextBus3": {
                "DestinationCode": "94009",
                "EstimatedArrival": "2023-09-03T17:54:01+08:00",
                "Feature": "WAB",
                "Latitude": "0.0",
                "Load": "SEA",
                "Longitude": "0.0",
                "OriginCode": "55509",
                "Type": "DD",
                "VisitNumber": "1"
            },
            "Operator": "SBST",
            "ServiceNo": "13"
        },
        {
            "NextBus": {
                "DestinationCode": "54009",
                "EstimatedArrival": "2023-09-03T17:32:18+08:00",
                "Feature": "WAB",
                "Latitude": "1.3794236666666666",
                "Load": "SEA",
                "Longitude": "103.83540883333333",
                "OriginCode": "54009",
                "Type": "SD",
                "VisitNumber": "1"
            },
            "NextBus2": {
                "DestinationCode": "54009",
                "EstimatedArrival": "2023-09-03T17:40:27+08:00",
                "Feature": "WAB",
                "Latitude": "1.3972646666666666",
                "Load": "SEA",
                "Longitude": "103.8184925",
                "OriginCode": "54009",
                "Type": "SD",
                "VisitNumber": "1"
            },
            "NextBus3": {
                "DestinationCode": "54009",
                "EstimatedArrival": "2023-09-03T17:47:12+08:00",
                "Feature": "WAB",
                "Latitude": "1.4155793333333333",
                "Load": "SEA",
                "Longitude": "103.803994",
                "OriginCode": "54009",
                "Type": "SD",
                "VisitNumber": "1"
            },
            "Operator": "SBST",
            "ServiceNo": "138"
        },
        {
            "NextBus": {
                "DestinationCode": "55509",
                "EstimatedArrival": "2023-09-03T17:32:04+08:00",
                "Feature": "WAB",
                "Latitude": "0.0",
                "Load": "SEA",
                "Longitude": "0.0",
                "OriginCode": "55509",
                "Type": "SD",
                "VisitNumber": "1"
            },
            "NextBus2": {
                "DestinationCode": "55509",
                "EstimatedArrival": "2023-09-03T17:47:04+08:00",
                "Feature": "WAB",
                "Latitude": "0.0",
                "Load": "SEA",
                "Longitude": "0.0",
                "OriginCode": "55509",
                "Type": "SD",
                "VisitNumber": "1"
            },
            "NextBus3": {
                "DestinationCode": "55509",
                "EstimatedArrival": "2023-09-03T18:02:09+08:00",
                "Feature": "WAB",
                "Latitude": "0.0",
                "Load": "SEA",
                "Longitude": "0.0",
                "OriginCode": "55509",
                "Type": "SD",
                "VisitNumber": "1"
            },
            "Operator": "SBST",
            "ServiceNo": "162M"
        },
        {
            "NextBus": {
                "DestinationCode": "10009",
                "EstimatedArrival": "2023-09-03T17:41:43+08:00",
                "Feature": "WAB",
                "Latitude": "1.4176873333333333",
                "Load": "SEA",
                "Longitude": "103.8335935",
                "OriginCode": "59009",
                "Type": "DD",
                "VisitNumber": "1"
            },
            "NextBus2": {
                "DestinationCode": "10009",
                "EstimatedArrival": "2023-09-03T17:49:07+08:00",
                "Feature": "WAB",
                "Latitude": "0.0",
                "Load": "SEA",
                "Longitude": "0.0",
                "OriginCode": "59009",
                "Type": "SD",
                "VisitNumber": "1"
            },
            "NextBus3": {
                "DestinationCode": "10009",
                "EstimatedArrival": "2023-09-03T17:59:07+08:00",
                "Feature": "WAB",
                "Latitude": "0.0",
                "Load": "SEA",
                "Longitude": "0.0",
                "OriginCode": "59009",
                "Type": "DD",
                "VisitNumber": "1"
            },
            "Operator": "SBST",
            "ServiceNo": "851"
        },
        {
            "NextBus": {
                "DestinationCode": "05019",
                "EstimatedArrival": "2023-09-03T17:48:34+08:00",
                "Feature": "WAB",
                "Latitude": "0.0",
                "Load": "SEA",
                "Longitude": "0.0",
                "OriginCode": "59009",
                "Type": "SD",
                "VisitNumber": "1"
            },
            "NextBus2": {
                "DestinationCode": "",
                "EstimatedArrival": "",
                "Feature": "",
                "Latitude": "",
                "Load": "",
                "Longitude": "",
                "OriginCode": "",
                "Type": "",
                "VisitNumber": ""
            },
            "NextBus3": {
                "DestinationCode": "",
                "EstimatedArrival": "",
                "Feature": "",
                "Latitude": "",
                "Load": "",
                "Longitude": "",
                "OriginCode": "",
                "Type": "",
                "VisitNumber": ""
            },
            "Operator": "SBST",
            "ServiceNo": "851e"
        },
        {
            "NextBus": {
                "DestinationCode": "43009",
                "EstimatedArrival": "2023-09-03T17:40:57+08:00",
                "Feature": "WAB",
                "Latitude": "1.4174121666666668",
                "Load": "SEA",
                "Longitude": "103.83344616666666",
                "OriginCode": "59009",
                "Type": "SD",
                "VisitNumber": "1"
            },
            "NextBus2": {
                "DestinationCode": "43009",
                "EstimatedArrival": "2023-09-03T17:51:02+08:00",
                "Feature": "WAB",
                "Latitude": "0.0",
                "Load": "SEA",
                "Longitude": "0.0",
                "OriginCode": "59009",
                "Type": "SD",
                "VisitNumber": "1"
            },
            "NextBus3": {
                "DestinationCode": "43009",
                "EstimatedArrival": "2023-09-03T18:05:02+08:00",
                "Feature": "WAB",
                "Latitude": "0.0",
                "Load": "SEA",
                "Longitude": "0.0",
                "OriginCode": "59009",
                "Type": "SD",
                "VisitNumber": "1"
            },
            "Operator": "SBST",
            "ServiceNo": "852"
        },
        {
            "NextBus": {
                "DestinationCode": "94009",
                "EstimatedArrival": "2023-09-03T17:29:53+08:00",
                "Feature": "WAB",
                "Latitude": "1.3844371666666666",
                "Load": "SEA",
                "Longitude": "103.84371033333333",
                "OriginCode": "59009",
                "Type": "SD",
                "VisitNumber": "1"
            },
            "NextBus2": {
                "DestinationCode": "94009",
                "EstimatedArrival": "2023-09-03T17:43:05+08:00",
                "Feature": "WAB",
                "Latitude": "1.4231311666666666",
                "Load": "SEA",
                "Longitude": "103.83676433333333",
                "OriginCode": "59009",
                "Type": "DD",
                "VisitNumber": "1"
            },
            "NextBus3": {
                "DestinationCode": "94009",
                "EstimatedArrival": "2023-09-03T17:48:25+08:00",
                "Feature": "WAB",
                "Latitude": "0.0",
                "Load": "SEA",
                "Longitude": "0.0",
                "OriginCode": "59009",
                "Type": "SD",
                "VisitNumber": "1"
            },
            "Operator": "TTS",
            "ServiceNo": "853M"
        },
        {
            "NextBus": {
                "DestinationCode": "54009",
                "EstimatedArrival": "2023-09-03T17:39:24+08:00",
                "Feature": "WAB",
                "Latitude": "1.3891691666666666",
                "Load": "SEA",
                "Longitude": "103.86505966666667",
                "OriginCode": "67009",
                "Type": "SD",
                "VisitNumber": "1"
            },
            "NextBus2": {
                "DestinationCode": "54009",
                "EstimatedArrival": "2023-09-03T17:52:08+08:00",
                "Feature": "WAB",
                "Latitude": "1.4007853333333333",
                "Load": "SEA",
                "Longitude": "103.88934133333333",
                "OriginCode": "67009",
                "Type": "SD",
                "VisitNumber": "1"
            },
            "NextBus3": {
                "DestinationCode": "",
                "EstimatedArrival": "",
                "Feature": "",
                "Latitude": "",
                "Load": "",
                "Longitude": "",
                "OriginCode": "",
                "Type": "",
                "VisitNumber": ""
            },
            "Operator": "SBST",
            "ServiceNo": "86"
        }
    ],
    "odata.metadata": "http://datamall2.mytransport.sg/ltaodataservice/$metadata#BusArrivalv2/@Element"
}