{
    "BusStopCode": "56019",
    "Services": [
        {
            "NextBus": {
                "DestinationCode": "52009",
                "EstimatedArrival": "2023-09-03T17:27:16+08:00",
                "Feature": "WAB",
                "Latitude": "1.3767795",
                "Load": "SEA",
                "Longitude": "103.82849116666667",
                "OriginCode": "67009",
                "Type": "SD",
                "VisitNumber": "1"
            },
            "NextBus2": {
                "DestinationCode": "52009",
                "EstimatedArrival": "2023-09-03T17:44:04+08:00",
                "Feature": "WAB",
                "Latitude": "1.389249",
                "Load": "SDA",
                "Longitude": "103.86893566666667",
                "OriginCode": "67009",
                "Type": "SD",
                "VisitNumber": "1"
            },
            "NextBus3": {
                "DestinationCode": "52009",
                "EstimatedArrival": "2023-09-03T17:57:46+08:00",
                "Feature": "WAB",
                "Latitude": "1.3830983333333333",
                "Load": "SEA",
                "Longitude": "103.89862133333334",
                "OriginCode": "67009",
                "Type": "SD",
                "VisitNumber": "1"
            },
            "Operator": "SBST",
            "ServiceNo": "163"
        },
        {
            "NextBus": {
                "DestinationCode": "10009",
                "EstimatedArrival": "2023-09-03T17:53:13+08:00",
                "Feature": "WAB",
                "Latitude": "1.4480411666666666",
                "Load": "SEA",
                "Longitude": "103.82220666666667",
                "OriginCode": "58009",
                "Type": "SD",
                "VisitNumber": "1"
            },
            "NextBus2": {
                "DestinationCode": "10009",
                "EstimatedArrival": "2023-09-03T18:07:00+08:00",
                "Feature": "WAB",
                "Latitude": "0.0",
                "Load": "SEA",
                "Longitude": "0.0",
                "OriginCode": "58009",
                "Type": "SD",
                "VisitNumber": "1"
            },
            "NextBus3": {
                "DestinationCode": "",
                "EstimatedArrival": "",
                "Feature": "",
                "Latitude": "",
                "Load": "",
                "Longitude": "",
                "OriginCode": "",
                "Type": "",
                "VisitNumber": ""
            },
            "Operator": "TTS",
            "ServiceNo": "167"
        },
        {
            "NextBus": {
                "DestinationCode": "54009",
                "EstimatedArrival": "2023-09-03T17:29:12+08:00",
                "Feature": "WAB",
                "Latitude": "1.3797825000000001",
                "Load": "SEA",
                "Longitude": "103.82746083333333",
                "OriginCode": "46009",
                "Type": "DD",
                "VisitNumber": "1"
            },
            "NextBus2": {
                "DestinationCode": "54009",
                "EstimatedArrival": "2023-09-03T17:43:46+08:00",
                "Feature": "WAB",
                "Latitude": "1.4228436666666666",
                "Load": "SEA",
                "Longitude": "103.83352583333334",
                "OriginCode": "46009",
                "Type": "DD",
                "VisitNumber": "1"
            },
            "NextBus3": {
                "DestinationCode": "54009",
                "EstimatedArrival": "2023-09-03T17:57:01+08:00",
                "Feature": "WAB",
                "Latitude": "1.4469023333333333",
                "Load": "SDA",
                "Longitude": "103.82774116666667",
                "OriginCode": "46009",
                "Type": "DD",
                "VisitNumber": "1"
            },
            "Operator": "TTS",
            "ServiceNo": "169"
        },
        {
            "NextBus": {
                "DestinationCode": "14009",
                "EstimatedArrival": "2023-09-03T17:26:05+08:00",
                "Feature": "WAB",
                "Latitude": "1.3734106666666666",
                "Load": "SEA",
                "Longitude": "103.82866183333333",
                "OriginCode": "59009",
                "Type": "SD",
                "VisitNumber": "1"
            },
            "NextBus2": {
                "DestinationCode": "14009",
                "EstimatedArrival": "2023-09-03T17:38:20+08:00",
                "Feature": "WAB",
                "Latitude": "1.4036448333333333",
                "Load": "SEA",
                "Longitude": "103.82750566666667",
                "OriginCode": "59009",
                "Type": "SD",
                "VisitNumber": "1"
            },
            "NextBus3": {
                "DestinationCode": "14009",
                "EstimatedArrival": "2023-09-03T17:46:50+08:00",
                "Feature": "WAB",
                "Latitude": "0.0",
                "Load": "SEA",
                "Longitude": "0.0",
                "OriginCode": "59009",
                "Type": "SD",
                "VisitNumber": "1"
            },
            "Operator": "TTS",
            "ServiceNo": "855"
        },
        {
            "NextBus": {
                "DestinationCode": "80009",
                "EstimatedArrival": "2023-09-03T17:25:57+08:00",
                "Feature": "WAB",
                "Latitude": "1.3718693333333334",
                "Load": "SEA",
                "Longitude": "103.8286855",
                "OriginCode": "58009",
                "Type": "SD",
                "VisitNumber": "1"
            },
            "NextBus2": {
                "DestinationCode": "80009",
                "EstimatedArrival": "2023-09-03T17:42:27+08:00",
                "Feature": "WAB",
                "Latitude": "1.4263731666666666",
                "Load": "SEA",
                "Longitude": "103.82640933333333",
                "OriginCode": "58009",
                "Type": "DD",
                "VisitNumber": "1"
            },
            "NextBus3": {
                "DestinationCode": "80009",
                "EstimatedArrival": "2023-09-03T17:57:57+08:00",
                "Feature": "WAB",
                "Latitude": "1.4517558333333334",
                "Load": "SEA",
                "Longitude": "103.81972166666667",
                "OriginCode": "58009",
                "Type": "DD",
                "VisitNumber": "1"
            },
            "Operator": "TTS",
            "ServiceNo": "980"
        }
    ],
    "odata.metadata": "http://datamall2.mytransport.sg/ltaodataservice/$metadata#BusArrivalv2/@Element"
}