{
    "BusStopCode": "72179",
    "Services": [
        {
            "NextBus": {
                "DestinationCode": "77009",
                "EstimatedArrival": "2023-09-03T17:30:48+08:00",
                "Feature": "WAB",
                "Latitude": "1.3453141666666666",
                "Load": "SEA",
                "Longitude": "103.93621616666667",
                "OriginCode": "77009",
                "Type": "SD",
                "VisitNumber": "1"
            },
            "NextBus2": {
                "DestinationCode": "77009",
                "EstimatedArrival": "2023-09-03T17:36:30+08:00",
                "Feature": "WAB",
                "Latitude": "1.3502501666666666",
                "Load": "SEA",
                "Longitude": "103.94165433333333",
                "OriginCode": "77009",
                "Type": "SD",
                "VisitNumber": "1"
            },
            "NextBus3": {
                "DestinationCode": "77009",
                "EstimatedArrival": "2023-09-03T17:53:19+08:00",
                "Feature": "WAB",
                "Latitude": "1.3754601666666666",
                "Load": "SEA",
                "Longitude": "103.94660266666666",
                "OriginCode": "77009",
                "Type": "SD",
                "VisitNumber": "1"
            },
            "Operator": "GAS",
            "ServiceNo": "15"
        },
        {
            "NextBus": {
                "DestinationCode": "75009",
                "EstimatedArrival": "2023-09-03T17:33:14+08:00",
                "Feature": "WAB",
                "Latitude": "1.3447248333333333",
                "Load": "SEA",
                "Longitude": "103.93994083333334",
                "OriginCode": "75009",
                "Type": "DD",
                "VisitNumber": "1"
            },
            "NextBus2": {
                "DestinationCode": "75009",
                "EstimatedArrival": "2023-09-03T17:41:31+08:00",
                "Feature": "WAB",
                "Latitude": "0.0",
                "Load": "SEA",
                "Longitude": "0.0",
                "OriginCode": "75009",
                "Type": "DD",
                "VisitNumber": "1"
            },
            "NextBus3": {
                "DestinationCode": "75009",
                "EstimatedArrival": "2023-09-03T17:53:31+08:00",
                "Feature": "WAB",
                "Latitude": "0.0",
                "Load": "SEA",
                "Longitude": "0.0",
                "OriginCode": "75009",
                "Type": "DD",
                "VisitNumber": "1"
            },
            "Operator": "SBST",
            "ServiceNo": "23"
        },
        {
            "NextBus": {
                "DestinationCode": "77009",
                "EstimatedArrival": "2023-09-03T17:26:02+08:00",
                "Feature": "WAB",
                "Latitude": "1.3465",
                "Load": "SEA",
                "Longitude": "103.92104716666667",
                "OriginCode": "77009",
                "Type": "SD",
                "VisitNumber": "1"
            },
            "NextBus2": {
                "DestinationCode": "77009",
                "EstimatedArrival": "2023-09-03T17:41:08+08:00",
                "Feature": "WAB",
                "Latitude": "1.3531966666666666",
                "Load": "SEA",
                "Longitude": "103.9551715",
                "OriginCode": "77009",
                "Type": "DD",
                "VisitNumber": "1"
            },
            "NextBus3": {
                "DestinationCode": "77009",
                "EstimatedArrival": "2023-09-03T17:59:48+08:00",
                "Feature": "WAB",
                "Latitude": "1.3717908333333333",
                "Load": "SEA",
                "Longitude": "103.94800433333333",
                "OriginCode": "77009",
                "Type": "DD",
                "VisitNumber": "1"
            },
            "Operator": "GAS",
            "ServiceNo": "518"
        },
        {
            "NextBus": {
                "DestinationCode": "53009",
                "EstimatedArrival": "2023-09-03T17:36:49+08:00",
                "Feature": "WAB",
                "Latitude": "1.3741161666666666",
                "Load": "SEA",
                "Longitude": "103.93124233333333",
                "OriginCode": "77009",
                "Type": "DD",
                "VisitNumber": "1"
            },
            "NextBus2": {
                "DestinationCode": "53009",
                "EstimatedArrival": "2023-09-03T17:47:28+08:00",
                "Feature": "WAB",
                "Latitude": "1.3764598333333333",
                "Load": "SEA",
                "Longitude": "103.94636966666667",
                "OriginCode": "77009",
                "Type": "DD",
                "VisitNumber": "1"
            },
            "NextBus3": {
                "DestinationCode": "53009",
                "EstimatedArrival": "2023-09-03T18:00:11+08:00",
                "Feature": "WAB",
                "Latitude": "0.0",
                "Load": "SEA",
                "Longitude": "0.0",
                "OriginCode": "77009",
                "Type": "DD",
                "VisitNumber": "1"
            },
            "Operator": "SBST",
            "ServiceNo": "58"
        },
        {
            "NextBus": {
                "DestinationCode": "52009",
                "EstimatedArrival": "2023-09-03T17:35:07+08:00",
                "Feature": "WAB",
                "Latitude": "1.3461105",
                "Load": "SEA",
                "Longitude": "103.94278833333334",
                "OriginCode": "75009",
                "Type": "SD",
                "VisitNumber": "1"
            },
            "NextBus2": {
                "DestinationCode": "52009",
                "EstimatedArrival": "2023-09-03T17:43:59+08:00",
                "Feature": "WAB",
                "Latitude": "1.3562901666666667",
                "Load": "SEA",
                "Longitude": "103.95528283333333",
                "OriginCode": "75009",
                "Type": "DD",
                "VisitNumber": "1"
            },
            "NextBus3": {
                "DestinationCode": "52009",
                "EstimatedArrival": "2023-09-03T17:54:20+08:00",
                "Feature": "WAB",
                "Latitude": "0.0",
                "Load": "SEA",
                "Longitude": "0.0",
                "OriginCode": "75009",
                "Type": "SD",
                "VisitNumber": "1"
            },
            "Operator": "SBST",
            "ServiceNo": "8"
        }
    ],
    "odata.metadata": "http://datamall2.mytransport.sg/ltaodataservice/$metadata#BusArrivalv2/@Element"
}