{
    "BusStopCode": "75271",
    "Services": [
        {
            "NextBus": {
                "DestinationCode": "75009",
                "EstimatedArrival": "2023-09-04T19:02:06+08:00",
                "Feature": "WAB",
                "Latitude": "1.3576793333333335",
                "Load": "SEA",
                "Longitude": "103.94042616666667",
                "OriginCode": "75009",
                "Type": "DD",
                "VisitNumber": "1"
            },
            "NextBus2": {
                "DestinationCode": "75009",
                "EstimatedArrival": "2023-09-04T19:11:33+08:00",
                "Feature": "WAB",
                "Latitude": "0.0",
                "Load": "SEA",
                "Longitude": "0.0",
                "OriginCode": "75009",
                "Type": "DD",
                "VisitNumber": "1"
            },
            "NextBus3": {
                "DestinationCode": "75009",
                "EstimatedArrival": "2023-09-04T19:21:33+08:00",
                "Feature": "WAB",
                "Latitude": "0.0",
                "Load": "SEA",
                "Longitude": "0.0",
                "OriginCode": "75009",
                "Type": "SD",
                "VisitNumber": "1"
            },
            "Operator": "SBST",
            "ServiceNo": "127"
        },
        {
            "NextBus": {
                "DestinationCode": "46009",
                "EstimatedArrival": "2023-09-04T18:59:05+08:00",
                "Feature": "WAB",
                "Latitude": "1.3602961666666666",
                "Load": "SDA",
                "Longitude": "103.93598583333333",
                "OriginCode": "84009",
                "Type": "DD",
                "VisitNumber": "1"
            },
            "NextBus2": {
                "DestinationCode": "46009",
                "EstimatedArrival": "2023-09-04T19:02:01+08:00",
                "Feature": "WAB",
                "Latitude": "1.3586851666666666",
                "Load": "SEA",
                "Longitude": "103.94208433333333",
                "OriginCode": "84009",
                "Type": "DD",
                "VisitNumber": "1"
            },
            "NextBus3": {
                "DestinationCode": "46009",
                "EstimatedArrival": "2023-09-04T19:13:51+08:00",
                "Feature": "WAB",
                "Latitude": "1.3475055",
                "Load": "SEA",
                "Longitude": "103.94216266666666",
                "OriginCode": "84009",
                "Type": "DD",
                "VisitNumber": "1"
            },
            "Operator": "SBST",
            "ServiceNo": "168"
        },
        {
            "NextBus": {
                "DestinationCode": "74009",
                "EstimatedArrival": "2023-09-04T19:12:26+08:00",
                "Feature": "WAB",
                "Latitude": "1.3564441666666667",
                "Load": "SEA",
                "Longitude": "103.95737516666667",
                "OriginCode": "84299",
                "Type": "SD",
                "VisitNumber": "1"
            },
            "NextBus2": {
                "DestinationCode": "74009",
                "EstimatedArrival": "2023-09-04T19:24:28+08:00",
                "Feature": "WAB",
                "Latitude": "1.3507256666666667",
                "Load": "SEA",
                "Longitude": "103.95283183333333",
                "OriginCode": "84299",
                "Type": "SD",
                "VisitNumber": "1"
            },
            "NextBus3": {
                "DestinationCode": "74009",
                "EstimatedArrival": "2023-09-04T19:42:44+08:00",
                "Feature": "WAB",
                "Latitude": "1.3333315",
                "Load": "SEA",
                "Longitude": "103.93893783333333",
                "OriginCode": "84299",
                "Type": "SD",
                "VisitNumber": "1"
            },
            "Operator": "SBST",
            "ServiceNo": "18"
        },
        {
            "NextBus": {
                "DestinationCode": "64009",
                "EstimatedArrival": "2023-09-04T18:59:08+08:00",
                "Feature": "WAB",
                "Latitude": "1.3602996666666667",
                "Load": "SDA",
                "Longitude": "103.93612416666667",
                "OriginCode": "64009",
                "Type": "SD",
                "VisitNumber": "1"
            },
            "NextBus2": {
                "DestinationCode": "64009",
                "EstimatedArrival": "2023-09-04T19:05:05+08:00",
                "Feature": "WAB",
                "Latitude": "1.3560401666666666",
                "Load": "SDA",
                "Longitude": "103.9462235",
                "OriginCode": "64009",
                "Type": "SD",
                "VisitNumber": "1"
            },
            "NextBus3": {
                "DestinationCode": "64009",
                "EstimatedArrival": "2023-09-04T19:10:21+08:00",
                "Feature": "WAB",
                "Latitude": "0.0",
                "Load": "SEA",
                "Longitude": "0.0",
                "OriginCode": "76131",
                "Type": "SD",
                "VisitNumber": "1"
            },
            "Operator": "SBST",
            "ServiceNo": "27"
        },
        {
            "NextBus": {
                "DestinationCode": "55509",
                "EstimatedArrival": "2023-09-04T18:59:59+08:00",
                "Feature": "WAB",
                "Latitude": "1.3581163333333333",
                "Load": "SEA",
                "Longitude": "103.9380755",
                "OriginCode": "75009",
                "Type": "DD",
                "VisitNumber": "1"
            },
            "NextBus2": {
                "DestinationCode": "55509",
                "EstimatedArrival": "2023-09-04T19:07:11+08:00",
                "Feature": "WAB",
                "Latitude": "1.3549965",
                "Load": "SEA",
                "Longitude": "103.94316566666667",
                "OriginCode": "75009",
                "Type": "DD",
                "VisitNumber": "1"
            },
            "NextBus3": {
                "DestinationCode": "55509",
                "EstimatedArrival": "2023-09-04T19:07:32+08:00",
                "Feature": "WAB",
                "Latitude": "0.0",
                "Load": "SEA",
                "Longitude": "0.0",
                "OriginCode": "75009",
                "Type": "DD",
                "VisitNumber": "1"
            },
            "Operator": "SBST",
            "ServiceNo": "72"
        }
    ],
    "odata.metadata": "http://datamall2.mytransport.sg/ltaodataservice/$metadata#BusArrivalv2/@Element"
}