{
    "BusStopCode": "82229",
    "Services": [
        {
            "NextBus": {
                "DestinationCode": "22009",
                "EstimatedArrival": "2023-09-04T19:04:01+08:00",
                "Feature": "WAB",
                "Latitude": "0.0",
                "Load": "SEA",
                "Longitude": "0.0",
                "OriginCode": "82009",
                "Type": "DD",
                "VisitNumber": "1"
            },
            "NextBus2": {
                "DestinationCode": "22009",
                "EstimatedArrival": "2023-09-04T19:11:13+08:00",
                "Feature": "WAB",
                "Latitude": "0.0",
                "Load": "SEA",
                "Longitude": "0.0",
                "OriginCode": "82009",
                "Type": "SD",
                "VisitNumber": "1"
            },
            "NextBus3": {
                "DestinationCode": "22009",
                "EstimatedArrival": "2023-09-04T19:25:13+08:00",
                "Feature": "WAB",
                "Latitude": "0.0",
                "Load": "SEA",
                "Longitude": "0.0",
                "OriginCode": "82009",
                "Type": "DD",
                "VisitNumber": "1"
            },
            "Operator": "SBST",
            "ServiceNo": "154"
        },
        {
            "NextBus": {
                "DestinationCode": "55509",
                "EstimatedArrival": "2023-09-04T19:04:01+08:00",
                "Feature": "WAB",
                "Latitude": "0.0",
                "Load": "SEA",
                "Longitude": "0.0",
                "OriginCode": "82009",
                "Type": "DD",
                "VisitNumber": "1"
            },
            "NextBus2": {
                "DestinationCode": "55509",
                "EstimatedArrival": "2023-09-04T19:17:08+08:00",
                "Feature": "WAB",
                "Latitude": "0.0",
                "Load": "SEA",
                "Longitude": "0.0",
                "OriginCode": "82009",
                "Type": "SD",
                "VisitNumber": "1"
            },
            "NextBus3": {
                "DestinationCode": "55509",
                "EstimatedArrival": "2023-09-04T19:30:08+08:00",
                "Feature": "WAB",
                "Latitude": "0.0",
                "Load": "SEA",
                "Longitude": "0.0",
                "OriginCode": "82009",
                "Type": "DD",
                "VisitNumber": "1"
            },
            "Operator": "SBST",
            "ServiceNo": "76"
        }
    ],
    "odata.metadata": "http://datamall2.mytransport.sg/ltaodataservice/$metadata#BusArrivalv2/@Element"
}