{
    "BusStopCode": "96019",
    "Services": [
        {
            "NextBus": {
                "DestinationCode": "10499",
                "EstimatedArrival": "2023-09-03T17:36:23+08:00",
                "Feature": "WAB",
                "Latitude": "1.3475046666666666",
                "Load": "SEA",
                "Longitude": "103.9578815",
                "OriginCode": "77009",
                "Type": "DD",
                "VisitNumber": "1"
            },
            "NextBus2": {
                "DestinationCode": "10499",
                "EstimatedArrival": "2023-09-03T17:48:42+08:00",
                "Feature": "WAB",
                "Latitude": "1.3642918333333334",
                "Load": "SEA",
                "Longitude": "103.96116166666667",
                "OriginCode": "77009",
                "Type": "SD",
                "VisitNumber": "1"
            },
            "NextBus3": {
                "DestinationCode": "10499",
                "EstimatedArrival": "2023-09-03T18:01:37+08:00",
                "Feature": "WAB",
                "Latitude": "0.0",
                "Load": "SEA",
                "Longitude": "0.0",
                "OriginCode": "77009",
                "Type": "DD",
                "VisitNumber": "1"
            },
            "Operator": "GAS",
            "ServiceNo": "12"
        },
        {
            "NextBus": {
                "DestinationCode": "54009",
                "EstimatedArrival": "2023-09-03T17:28:58+08:00",
                "Feature": "WAB",
                "Latitude": "1.3331731666666666",
                "Load": "SDA",
                "Longitude": "103.95595183333333",
                "OriginCode": "54009",
                "Type": "SD",
                "VisitNumber": "1"
            },
            "NextBus2": {
                "DestinationCode": "54009",
                "EstimatedArrival": "2023-09-03T17:40:32+08:00",
                "Feature": "WAB",
                "Latitude": "1.3386968333333333",
                "Load": "SEA",
                "Longitude": "103.98246166666667",
                "OriginCode": "54009",
                "Type": "SD",
                "VisitNumber": "1"
            },
            "NextBus3": {
                "DestinationCode": "54009",
                "EstimatedArrival": "2023-09-03T17:54:30+08:00",
                "Feature": "WAB",
                "Latitude": "1.3605783333333332",
                "Load": "SEA",
                "Longitude": "103.9881",
                "OriginCode": "54009",
                "Type": "SD",
                "VisitNumber": "1"
            },
            "Operator": "SBST",
            "ServiceNo": "24"
        },
        {
            "NextBus": {
                "DestinationCode": "52009",
                "EstimatedArrival": "2023-09-03T17:29:44+08:00",
                "Feature": "WAB",
                "Latitude": "1.3388986666666667",
                "Load": "SEA",
                "Longitude": "103.9492555",
                "OriginCode": "75009",
                "Type": "DD",
                "VisitNumber": "1"
            },
            "NextBus2": {
                "DestinationCode": "52009",
                "EstimatedArrival": "2023-09-03T17:37:17+08:00",
                "Feature": "WAB",
                "Latitude": "0.0",
                "Load": "SEA",
                "Longitude": "0.0",
                "OriginCode": "75009",
                "Type": "DD",
                "VisitNumber": "1"
            },
            "NextBus3": {
                "DestinationCode": "52009",
                "EstimatedArrival": "2023-09-03T17:48:17+08:00",
                "Feature": "WAB",
                "Latitude": "0.0",
                "Load": "SEA",
                "Longitude": "0.0",
                "OriginCode": "75009",
                "Type": "DD",
                "VisitNumber": "1"
            },
            "Operator": "SBST",
            "ServiceNo": "31"
        },
        {
            "NextBus": {
                "DestinationCode": "84009",
                "EstimatedArrival": "2023-09-03T17:34:57+08:00",
                "Feature": "WAB",
                "Latitude": "1.3423915",
                "Load": "SDA",
                "Longitude": "103.95361266666667",
                "OriginCode": "75009",
                "Type": "SD",
                "VisitNumber": "1"
            },
            "NextBus2": {
                "DestinationCode": "84009",
                "EstimatedArrival": "2023-09-03T17:46:11+08:00",
                "Feature": "WAB",
                "Latitude": "1.3554485",
                "Load": "SEA",
                "Longitude": "103.95558116666666",
                "OriginCode": "75009",
                "Type": "SD",
                "VisitNumber": "1"
            },
            "NextBus3": {
                "DestinationCode": "84009",
                "EstimatedArrival": "2023-09-03T17:54:34+08:00",
                "Feature": "WAB",
                "Latitude": "0.0",
                "Load": "SEA",
                "Longitude": "0.0",
                "OriginCode": "75009",
                "Type": "SD",
                "VisitNumber": "1"
            },
            "Operator": "SBST",
            "ServiceNo": "38"
        },
        {
            "NextBus": {
                "DestinationCode": "97009",
                "EstimatedArrival": "2023-09-03T17:35:07+08:00",
                "Feature": "WAB",
                "Latitude": "0.0",
                "Load": "SEA",
                "Longitude": "0.0",
                "OriginCode": "97009",
                "Type": "SD",
                "VisitNumber": "1"
            },
            "NextBus2": {
                "DestinationCode": "97009",
                "EstimatedArrival": "2023-09-03T17:49:07+08:00",
                "Feature": "WAB",
                "Latitude": "0.0",
                "Load": "SEA",
                "Longitude": "0.0",
                "OriginCode": "97009",
                "Type": "SD",
                "VisitNumber": "1"
            },
            "NextBus3": {
                "DestinationCode": "97009",
                "EstimatedArrival": "2023-09-03T18:03:07+08:00",
                "Feature": "WAB",
                "Latitude": "0.0",
                "Load": "SEA",
                "Longitude": "0.0",
                "OriginCode": "97009",
                "Type": "DD",
                "VisitNumber": "1"
            },
            "Operator": "SBST",
            "ServiceNo": "47"
        }
    ],
    "odata.metadata": "http://datamall2.mytransport.sg/ltaodataservice/$metadata#BusArrivalv2/@Element"
}